{"best-practices.md":"fmfRH87l","bootstrap.md":"CXhE4CIn","control-flow.md":"mB4GLIfj","definitions.md":"BaO23tJ-","dotnet-integration.md":"5SvGzq3J","expressions.md":"DFa7gFPn","functional-programming.md":"DJy4Ms2F","generics.md":"BkexD9_5","getting-started.md":"MZaL-Dvu","grammar.md":"BXvLPCfF","history.md":"BDGyy02O","implementation.md":"B8OLATKu","index.md":"CXTrG27d","known-issues.md":"BtoKC8G9","language-basics.md":"4ZEsprzT","object-oriented-programming.md":"CCO_r4sW","resources.md":"DS1Q_mzl","syntax.md":"pcsGencd","todo.md":"Csjz4zaU","tooling.md":"xthjzq3-","type-inference.md":"CXAjc8Y6"}
